gitlab_issues_sync/__init__.py
gitlab_issues_sync/__main__.py
gitlab_issues_sync/cli/__init__.py
gitlab_issues_sync/cli/main.py
gitlab_issues_sync-1.1.0.dist-info/LICENSE
gitlab_issues_sync-1.1.0.dist-info/METADATA
gitlab_issues_sync-1.1.0.dist-info/WHEEL
gitlab_issues_sync-1.1.0.dist-info/entry_points.txt
gitlab_issues_sync-1.1.0.dist-info/top_level.txt
gitlab_issues_sync-1.1.0.dist-info/RECORD
