Metadata-Version: 2.1
Name: gitlab-issues-sync
Version: 1.1.0
Summary: Synchronize issues from a GitLab project to another
Home-page: https://gitlab.com/AdrianDC/gitlab-issues-sync
Author: Adrian DC
Author-email: radian.dc@gmail.com
License: Apache License 2.0
Project-URL: Changelog, https://gitlab.com/AdrianDC/gitlab-issues-sync/blob/master/CHANGELOG.md
Project-URL: Documentation, https://gitlab.com/AdrianDC/gitlab-issues-sync#gitlab-issues-sync
Keywords: gitlab issues sync
Classifier: Environment :: Console
Classifier: Intended Audience :: Developers
Classifier: License :: OSI Approved :: Apache Software License
Classifier: Operating System :: OS Independent
Classifier: Programming Language :: Python :: 3
Classifier: Programming Language :: Python :: 3.6
Classifier: Programming Language :: Python :: 3.7
Classifier: Programming Language :: Python :: 3.8
Classifier: Programming Language :: Python :: 3.9
Classifier: Programming Language :: Python :: 3.10
Classifier: Topic :: Software Development
Classifier: Topic :: Utilities
Requires-Python: >=3, !=3.0.*, !=3.1.*, !=3.2.*, !=3.3.*, !=3.4.*, !=3.5.*
License-File: LICENSE
Requires-Dist: python-gitlab (>=2.1.2)
Requires-Dist: setuptools (>=45.1.0)
